PlexPreferNonForcedSubs/PlexPreferNonForcedSubs.py
PlexPreferNonForcedSubs/__init__.py
PlexPreferNonForcedSubs-2.1.8.dist-info/LICENSE
PlexPreferNonForcedSubs-2.1.8.dist-info/METADATA
PlexPreferNonForcedSubs-2.1.8.dist-info/WHEEL
PlexPreferNonForcedSubs-2.1.8.dist-info/entry_points.txt
PlexPreferNonForcedSubs-2.1.8.dist-info/top_level.txt
PlexPreferNonForcedSubs-2.1.8.dist-info/RECORD
