Metadata-Version: 2.1
Name: PlexPreferNonForcedSubs
Version: 2.1.8
Summary: This script will set all movies and shows in your local Plex library to English non forced subtitles by default.
Home-page: https://github.com/RileyXX/PlexPreferNonForcedSubs
Author: RileyXX
Keywords: python,video,plex,subtitles,subs
Classifier: Development Status :: 5 - Production/Stable
Classifier: Intended Audience :: End Users/Desktop
Classifier: Programming Language :: Python :: 3
Classifier: Operating System :: OS Independent
Requires-Python: >=3.5
License-File: LICENSE
Requires-Dist: plexapi
